cgparser.py
dot.py
reader.py
setup.py
bin/cg2dot
bin/cgsplit
bin/xdot-pygoocanvas
stylers/__init__.py
stylers/default.py
xdebugtoolkit.egg-info/PKG-INFO
xdebugtoolkit.egg-info/SOURCES.txt
xdebugtoolkit.egg-info/dependency_links.txt
xdebugtoolkit.egg-info/top_level.txt