Metadata-Version: 1.0
Name: xdebugtoolkit
Version: 0.2.3-1
Summary: A toolkit for splitting, aggregating, analyzing and visualizing xdebug cachegrind files
Home-page: https://github.com/AlexeyKupershtokh/xdebugtoolkit
Author: Alexey Kupershtokh
Author-email: alexey.kupershtokh@gmail.com
License: LGPL
Platform: UNKNOWN
